telegraph_mcp/__init__.py
telegraph_mcp/__main__.py
telegraph_mcp/prompts.py
telegraph_mcp/py.typed
telegraph_mcp/resources.py
telegraph_mcp/server.py
telegraph_mcp/tools/__init__.py
telegraph_mcp/tools/account.py
telegraph_mcp/tools/export.py
telegraph_mcp/tools/pages.py
telegraph_mcp/tools/templates.py
telegraph_mcp_py-1.0.0.dist-info/licenses/LICENSE
telegraph_mcp_py-1.0.0.dist-info/METADATA
telegraph_mcp_py-1.0.0.dist-info/WHEEL
telegraph_mcp_py-1.0.0.dist-info/entry_points.txt
telegraph_mcp_py-1.0.0.dist-info/top_level.txt
telegraph_mcp_py-1.0.0.dist-info/RECORD
