Metadata-Version: 2.4
Name: telegraph-mcp-py
Version: 1.0.0
Summary: MCP server for Telegraph API - create and manage Telegraph pages with Claude and other LLM clients
Author: Nehorai Hadad
Maintainer: Nehorai Hadad
License: MIT
Project-URL: Homepage, https://github.com/NehoraiHadad/telegraph-mcp
Project-URL: Documentation, https://github.com/NehoraiHadad/telegraph-mcp/tree/main/telegraph-mcp-py#readme
Project-URL: Repository, https://github.com/NehoraiHadad/telegraph-mcp
Project-URL: Bug Tracker, https://github.com/NehoraiHadad/telegraph-mcp/issues
Project-URL: Changelog, https://github.com/NehoraiHadad/telegraph-mcp/releases
Keywords: mcp,model-context-protocol,telegraph,telegraph-api,telegra.ph,claude,anthropic,ai,llm,publishing,blogging
Classifier: Development Status :: 4 - Beta
Classifier: Intended Audience :: Developers
Classifier: License :: OSI Approved :: MIT License
Classifier: Operating System :: OS Independent
Classifier: Programming Language :: Python
Classifier: Programming Language :: Python :: 3
Classifier: Programming Language :: Python :: 3.10
Classifier: Programming Language :: Python :: 3.11
Classifier: Programming Language :: Python :: 3.12
Classifier: Programming Language :: Python :: 3.13
Classifier: Programming Language :: Python :: Implementation :: CPython
Classifier: Topic :: Internet
Classifier: Topic :: Software Development :: Libraries
Classifier: Topic :: Software Development :: Libraries :: Python Modules
Classifier: Topic :: Communications
Classifier: Typing :: Typed
Requires-Python: >=3.10
License-File: LICENSE
Requires-Dist: mcp>=1.0.0
Requires-Dist: telegraph-api-py>=1.0.0
Provides-Extra: dev
Requires-Dist: pytest>=7.0.0; extra == "dev"
Requires-Dist: pytest-asyncio>=0.21.0; extra == "dev"
Requires-Dist: black>=23.0.0; extra == "dev"
Requires-Dist: mypy>=1.0.0; extra == "dev"
Requires-Dist: ruff>=0.1.0; extra == "dev"
Dynamic: license-file
